pit/__init__.py
pit/__main__.py
pit/cli.py
pit/echoes.py
pit/groups.py
pit/utils.py
snake_pit-0.3.0.dist-info/DESCRIPTION.rst
snake_pit-0.3.0.dist-info/METADATA
snake_pit-0.3.0.dist-info/RECORD
snake_pit-0.3.0.dist-info/WHEEL
snake_pit-0.3.0.dist-info/entry_points.txt
snake_pit-0.3.0.dist-info/metadata.json
snake_pit-0.3.0.dist-info/top_level.txt
snakepit/__init__.py
snakepit/__main__.py
snakepit/_compat.py
snakepit/cli.py
snakepit/config.py
snakepit/dists.py
snakepit/echoes.py
snakepit/exceptions.py
snakepit/groups.py
snakepit/utils.py
snakepit/adapters/__init__.py
snakepit/adapters/pip.py
