Metadata-Version: 2.0
Name: snake-pit
Version: 0.3.0
Summary: Depending on the installation or uninstall packages, and then edit the requirements file.
Home-page: https://github.com/kk6/snake-pit
Author: kk6
Author-email: hiro.ashiya@gmail.com
License: MIT
Platform: UNKNOWN
Classifier: Development Status :: 3 - Alpha
Classifier: Intended Audience :: Developers
Classifier: License :: OSI Approved :: MIT License
Classifier: Programming Language :: Python
Classifier: Programming Language :: Python :: 2
Classifier: Programming Language :: Python :: 2.7
Classifier: Programming Language :: Python :: 3
Classifier: Programming Language :: Python :: 3.5
Classifier: Topic :: Utilities
Requires-Dist: Click
Requires-Dist: PyYAML
Requires-Dist: distlib
